deployto/__init__.py
deployto/cli.py
deployto/config.py
deployto/package.py
deployto/resources.py
deployto/deployment/__init__.py
deployto/deployment/awslambda.py
deployto/deployment/base.py
deployto/deployment/elasticbeanstalk.py
deployto-0.1.4.dist-info/DESCRIPTION.rst
deployto-0.1.4.dist-info/METADATA
deployto-0.1.4.dist-info/RECORD
deployto-0.1.4.dist-info/WHEEL
deployto-0.1.4.dist-info/entry_points.txt
deployto-0.1.4.dist-info/metadata.json
deployto-0.1.4.dist-info/top_level.txt
