Metadata-Version: 2.0
Name: deployto
Version: 0.1.4
Summary: CloudFormation aware deployment tool
Home-page: https://github.com/flomotlik/deployto
Author: Florian Motlik
Author-email: flo@theserverlessway.com
License: MIT
Keywords: aws,cloud,awscli,deployment
Platform: UNKNOWN
Classifier: Intended Audience :: Developers
Classifier: Topic :: Utilities
Classifier: License :: Public Domain
Classifier: Natural Language :: English
Classifier: Operating System :: OS Independent
Classifier: Programming Language :: Python :: 2
Classifier: Programming Language :: Python :: 2.6
Classifier: Programming Language :: Python :: 2.7
Classifier: Programming Language :: Python :: 3
Classifier: Programming Language :: Python :: 3.2
Classifier: Programming Language :: Python :: 3.3
Classifier: Programming Language :: Python :: 3.4
Requires-Dist: boto3 (==1.6.4)
Requires-Dist: pyyaml (==3.12)
Requires-Dist: schematics (==2.0.1)
